git_notion/__init__.py
git_notion/cli.py
git_notion/git_notion.py
git_notion-0.2.4.dist-info/LICENSE
git_notion-0.2.4.dist-info/METADATA
git_notion-0.2.4.dist-info/WHEEL
git_notion-0.2.4.dist-info/entry_points.txt
git_notion-0.2.4.dist-info/top_level.txt
git_notion-0.2.4.dist-info/RECORD
