Metadata-Version: 2.1
Name: git-notion
Version: 0.2.4
Summary: Syncs Github Mmarkdown files to Notion
Home-page: https://github.com/NarekA/git-notion
Author: NarekA
License: MIT license
Keywords: git_notion
Platform: UNKNOWN
Classifier: Development Status :: 2 - Pre-Alpha
Classifier: Intended Audience :: Developers
Classifier: License :: OSI Approved :: MIT License
Classifier: Natural Language :: English
Classifier: Programming Language :: Python :: 3
Classifier: Programming Language :: Python :: 3.5
Classifier: Programming Language :: Python :: 3.6
Classifier: Programming Language :: Python :: 3.7
Classifier: Programming Language :: Python :: 3.8
Requires-Python: >=3.5
Requires-Dist: click
Requires-Dist: md2notion
